{
  "id": "yolov8s-architecture-breakdown",
  "name": "YOLOv8s Architecture Deep Dive",
  "difficulty": "Advanced",
  "description": "<h3>The Architecture of YOLOv8s</h3><p>YOLOv8 (You Only Look Once version 8) by Ultralytics represents the state-of-the-art in real-time object detection. The 's' variant (Small) balances speed and accuracy for edge deployment.</p><ul><li><b>Backbone:</b> A modified CSPDarknet53 that uses <b>C2f modules</b> (Cross-Stage Partial Bottleneck with two convolutions) to enhance gradient flow and reduce model size.</li><li><b>SPPF:</b> The Spatial Pyramid Pooling - Fast layer at the end of the backbone pools features at different scales into a fixed-size map.</li><li><b>Neck:</b> Uses a <b>PAN-FPN</b> (Path Aggregation Network) approach, facilitating both top-down and bottom-up feature fusion to combine high-level semantic info with low-level geometric info.</li><li><b>Head:</b> An <b>Anchor-Free Decoupled Head</b>. Unlike previous versions, it separates classification and regression (bounding box) tasks into two distinct branches, improving convergence.</li></ul>",
  "tags": [
    "Computer Vision",
    "Deep Learning",
    "YOLO",
    "Neural Networks",
    "Object Detection"
  ],
  "code": "graph TD\n  subgraph Input_Stage\n    IMG[Input Image 640x640x3] \n  end\n\n  subgraph Backbone\n    B1[Conv P1/2] --> B2[Conv P2/4]\n    B2 --> C2f1[C2f Module]\n    C2f1 --> B3[Conv P3/8]\n    B3 --> C2f2[C2f Module - P3 Output]\n    C2f2 --> B4[Conv P4/16]\n    B4 --> C2f3[C2f Module - P4 Output]\n    C2f3 --> B5[Conv P5/32]\n    B5 --> C2f4[C2f Module]\n    C2f4 --> SPPF[SPPF - Spatial Pyramid Pooling]\n  end\n\n  subgraph Neck_PAN_FPN\n    SPPF --> Up1[Upsample]\n    Up1 --- Concat1{Concat}\n    C2f3 --- Concat1\n    Concat1 --> C2f_N1[C2f Module]\n    \n    C2f_N1 --> Up2[Upsample]\n    Up2 --- Concat2{Concat}\n    C2f2 --- Concat2\n    Concat2 --> C2f_N2[C2f Module - P3 Scale]\n    \n    C2f_N2 --> Down1[Conv Downsample]\n    Down1 --- Concat3{Concat}\n    C2f_N1 --- Concat3\n    Concat3 --> C2f_N3[C2f Module - P4 Scale]\n    \n    C2f_N3 --> Down2[Conv Downsample]\n    Down2 --- Concat4{Concat}\n    SPPF --- Concat4\n    Concat4 --> C2f_N4[C2f Module - P5 Scale]\n  end\n\n  subgraph Decoupled_Head\n    C2f_N2 --> Head1[Decoupled Head: Small Objects]\n    C2f_N3 --> Head2[Decoupled Head: Medium Objects]\n    C2f_N4 --> Head3[Decoupled Head: Large Objects]\n    \n    Head1 --> Out[Class + Box Prediction]\n    Head2 --> Out\n    Head3 --> Out\n  end\n\n  IMG --> B1\n\n  %% Styling\n  classDef default fill:#f9f9f9,stroke:#333,stroke-width:1px,color:#000;\n  classDef highlight fill:#e1f5fe,stroke:#01579b,stroke-width:2px,color:#000;\n  classDef stage fill:#fff,stroke:#64748b,stroke-width:2px,stroke-dasharray: 5 5,color:#000;\n\n  style Input_Stage fill:transparent,stroke:#94a3b8,stroke-dasharray: 5 5\n  style Backbone fill:transparent,stroke:#94a3b8,stroke-dasharray: 5 5\n  style Neck_PAN_FPN fill:transparent,stroke:#94a3b8,stroke-dasharray: 5 5\n  style Decoupled_Head fill:transparent,stroke:#94a3b8,stroke-dasharray: 5 5\n\n  class C2f1,C2f2,C2f3,C2f4,C2f_N1,C2f_N2,C2f_N3,C2f_N4 highlight\n  class SPPF,Head1,Head2,Head3 highlight"
}